{
    "annotations": {
      "list": [
        {
          "builtIn": 1,
          "datasource": "-- Grafana --",
          "enable": true,
          "hide": true,
          "iconColor": "rgba(0, 211, 255, 1)",
          "name": "Annotations & Alerts",
          "type": "dashboard"
        }
      ]
    },
    "editable": true,
    "gnetId": null,
    "graphTooltip": 0,
    "id": 9,
    "links": [],
    "panels": [
      {
        "collapsed": true,
        "datasource": null,
        "gridPos": {
          "h": 1,
          "w": 24,
          "x": 0,
          "y": 0
        },
        "id": 9,
        "panels": [
          {
            "datasource": "Prometheus",
            "fieldConfig": {
              "defaults": {
                "color": {
                  "mode": "thresholds"
                },
                "mappings": [],
                "max": 100,
                "thresholds": {
                  "mode": "absolute",
                  "steps": [
                    {
                      "color": "green",
                      "value": null
                    },
                    {
                      "color": "red",
                      "value": 80
                    }
                  ]
                }
              },
              "overrides": []
            },
            "gridPos": {
              "h": 5,
              "w": 24,
              "x": 0,
              "y": 1
            },
            "id": 7,
            "options": {
              "reduceOptions": {
                "calcs": [
                  "lastNotNull"
                ],
                "fields": "",
                "values": false
              },
              "showThresholdLabels": false,
              "showThresholdMarkers": true,
              "text": {}
            },
            "pluginVersion": "7.5.7",
            "targets": [
              {
                "exemplar": true,
                "expr": "100 - (avg by (instance) (irate(node_cpu_seconds_total{mode=\"idle\"}[5m])) * 100)",
                "format": "time_series",
                "interval": "",
                "intervalFactor": 2,
                "legendFormat": "{{instance}}",
                "refId": "A"
              }
            ],
            "timeFrom": null,
            "timeShift": null,
            "title": "CPU  Usage",
            "type": "gauge"
          },
          {
            "datasource": "Prometheus",
            "fieldConfig": {
              "defaults": {
                "color": {
                  "mode": "thresholds"
                },
                "mappings": [],
                "max": 100,
                "min": 0,
                "thresholds": {
                  "mode": "absolute",
                  "steps": [
                    {
                      "color": "green",
                      "value": null
                    },
                    {
                      "color": "red",
                      "value": 80
                    }
                  ]
                }
              },
              "overrides": []
            },
            "gridPos": {
              "h": 5,
              "w": 24,
              "x": 0,
              "y": 6
            },
            "id": 11,
            "options": {
              "reduceOptions": {
                "calcs": [
                  "lastNotNull"
                ],
                "fields": "",
                "values": false
              },
              "showThresholdLabels": false,
              "showThresholdMarkers": true,
              "text": {}
            },
            "pluginVersion": "7.5.7",
            "targets": [
              {
                "exemplar": true,
                "expr": "100 - ((node_memory_MemAvailable_bytes* 100) / node_memory_MemTotal_bytes)",
                "interval": "",
                "legendFormat": "{{instance}}",
                "refId": "A"
              }
            ],
            "title": "MEM Usage",
            "type": "gauge"
          },
          {
            "datasource": "Prometheus",
            "fieldConfig": {
              "defaults": {
                "color": {
                  "mode": "thresholds"
                },
                "mappings": [],
                "max": 100,
                "min": 0,
                "thresholds": {
                  "mode": "absolute",
                  "steps": [
                    {
                      "color": "green",
                      "value": null
                    },
                    {
                      "color": "red",
                      "value": 80
                    }
                  ]
                }
              },
              "overrides": []
            },
            "gridPos": {
              "h": 5,
              "w": 24,
              "x": 0,
              "y": 11
            },
            "id": 15,
            "options": {
              "reduceOptions": {
                "calcs": [
                  "lastNotNull"
                ],
                "fields": "",
                "values": false
              },
              "showThresholdLabels": false,
              "showThresholdMarkers": true,
              "text": {}
            },
            "pluginVersion": "7.5.7",
            "targets": [
              {
                "exemplar": true,
                "expr": "sum by (instance)(100 - ((node_filesystem_avail_bytes{device!~'rootfs'} * 100) / node_filesystem_size_bytes{device!~'rootfs'}))",
                "interval": "",
                "legendFormat": "{{instance}}",
                "refId": "A"
              }
            ],
            "timeFrom": null,
            "timeShift": null,
            "title": "Disk Usage",
            "type": "gauge"
          }
        ],
        "title": "Gauge",
        "type": "row"
      },
      {
        "collapsed": false,
        "datasource": null,
        "gridPos": {
          "h": 1,
          "w": 24,
          "x": 0,
          "y": 1
        },
        "id": 2,
        "panels": [],
        "title": "Graph",
        "type": "row"
      },
      {
        "alert": {
          "alertRuleTags": {},
          "conditions": [
            {
              "evaluator": {
                "params": [
                  80
                ],
                "type": "gt"
              },
              "operator": {
                "type": "and"
              },
              "query": {
                "params": [
                  "A",
                  "5m",
                  "now"
                ]
              },
              "reducer": {
                "params": [],
                "type": "avg"
              },
              "type": "query"
            }
          ],
          "executionErrorState": "alerting",
          "for": "5m",
          "frequency": "1m",
          "handler": 1,
          "message": "",
          "name": "CPU Usage Alert",
          "noDataState": "alerting",
          "notifications": [
            {
              "uid": "4tC9VtRnk"
            }
          ]
        },
        "aliasColors": {},
        "bars": false,
        "dashLength": 10,
        "dashes": false,
        "datasource": "Prometheus",
        "fieldConfig": {
          "defaults": {},
          "overrides": []
        },
        "fill": 1,
        "fillGradient": 0,
        "gridPos": {
          "h": 8,
          "w": 12,
          "x": 0,
          "y": 2
        },
        "hiddenSeries": false,
        "id": 6,
        "legend": {
          "avg": false,
          "current": false,
          "max": false,
          "min": false,
          "show": true,
          "total": false,
          "values": false
        },
        "lines": true,
        "linewidth": 1,
        "nullPointMode": "null as zero",
        "options": {
          "alertThreshold": true
        },
        "percentage": false,
        "pluginVersion": "7.5.7",
        "pointradius": 2,
        "points": false,
        "renderer": "flot",
        "seriesOverrides": [],
        "spaceLength": 10,
        "stack": true,
        "steppedLine": false,
        "targets": [
          {
            "exemplar": true,
            "expr": "100 - (avg by (instance) (irate(node_cpu_seconds_total{mode=\"idle\"}[5m])) * 100)",
            "format": "time_series",
            "interval": "",
            "intervalFactor": 2,
            "legendFormat": "{{instance}}",
            "refId": "A"
          }
        ],
        "thresholds": [
          {
            "colorMode": "critical",
            "fill": true,
            "line": true,
            "op": "gt",
            "value": 80,
            "visible": true
          }
        ],
        "timeFrom": null,
        "timeRegions": [],
        "timeShift": null,
        "title": "CPU Graph",
        "tooltip": {
          "shared": true,
          "sort": 0,
          "value_type": "individual"
        },
        "type": "graph",
        "xaxis": {
          "buckets": null,
          "mode": "time",
          "name": null,
          "show": true,
          "values": []
        },
        "yaxes": [
          {
            "$$hashKey": "object:486",
            "format": "short",
            "label": "",
            "logBase": 1,
            "max": "102",
            "min": "0",
            "show": true
          },
          {
            "$$hashKey": "object:487",
            "format": "short",
            "label": null,
            "logBase": 1,
            "max": null,
            "min": null,
            "show": true
          }
        ],
        "yaxis": {
          "align": false,
          "alignLevel": null
        }
      },
      {
        "alert": {
          "alertRuleTags": {},
          "conditions": [
            {
              "evaluator": {
                "params": [
                  80
                ],
                "type": "gt"
              },
              "operator": {
                "type": "and"
              },
              "query": {
                "params": [
                  "A",
                  "5m",
                  "now"
                ]
              },
              "reducer": {
                "params": [],
                "type": "avg"
              },
              "type": "query"
            }
          ],
          "executionErrorState": "alerting",
          "for": "5m",
          "frequency": "1m",
          "handler": 1,
          "message": "",
          "name": "MEM Usage Alert",
          "noDataState": "alerting",
          "notifications": [
            {
              "uid": "4tC9VtRnk"
            }
          ]
        },
        "aliasColors": {},
        "bars": false,
        "dashLength": 10,
        "dashes": false,
        "datasource": "Prometheus",
        "fieldConfig": {
          "defaults": {},
          "overrides": []
        },
        "fill": 1,
        "fillGradient": 0,
        "gridPos": {
          "h": 8,
          "w": 12,
          "x": 12,
          "y": 2
        },
        "hiddenSeries": false,
        "id": 12,
        "legend": {
          "avg": false,
          "current": false,
          "max": false,
          "min": false,
          "show": true,
          "total": false,
          "values": false
        },
        "lines": true,
        "linewidth": 1,
        "nullPointMode": "null",
        "options": {
          "alertThreshold": true
        },
        "percentage": false,
        "pluginVersion": "7.5.7",
        "pointradius": 2,
        "points": false,
        "renderer": "flot",
        "seriesOverrides": [],
        "spaceLength": 10,
        "stack": false,
        "steppedLine": false,
        "targets": [
          {
            "exemplar": true,
            "expr": "100 - ((node_memory_MemAvailable_bytes* 100) / node_memory_MemTotal_bytes)",
            "interval": "",
            "legendFormat": "{{instance}}",
            "refId": "A"
          }
        ],
        "thresholds": [
          {
            "colorMode": "critical",
            "fill": true,
            "line": true,
            "op": "gt",
            "value": 80,
            "visible": true
          }
        ],
        "timeFrom": null,
        "timeRegions": [],
        "timeShift": null,
        "title": "MEM Graph",
        "tooltip": {
          "shared": true,
          "sort": 0,
          "value_type": "individual"
        },
        "type": "graph",
        "xaxis": {
          "buckets": null,
          "mode": "time",
          "name": null,
          "show": true,
          "values": []
        },
        "yaxes": [
          {
            "$$hashKey": "object:1899",
            "format": "short",
            "label": null,
            "logBase": 1,
            "max": "100",
            "min": "0",
            "show": true
          },
          {
            "$$hashKey": "object:1900",
            "format": "short",
            "label": null,
            "logBase": 1,
            "max": null,
            "min": null,
            "show": true
          }
        ],
        "yaxis": {
          "align": false,
          "alignLevel": null
        }
      },
      {
        "alert": {
          "alertRuleTags": {},
          "conditions": [
            {
              "evaluator": {
                "params": [
                  80
                ],
                "type": "gt"
              },
              "operator": {
                "type": "and"
              },
              "query": {
                "params": [
                  "A",
                  "5m",
                  "now"
                ]
              },
              "reducer": {
                "params": [],
                "type": "avg"
              },
              "type": "query"
            }
          ],
          "executionErrorState": "alerting",
          "for": "5m",
          "frequency": "1m",
          "handler": 1,
          "message": "",
          "name": "Disk Usage Alert",
          "noDataState": "alerting",
          "notifications": [
            {
              "uid": "4tC9VtRnk"
            }
          ]
        },
        "aliasColors": {},
        "bars": false,
        "dashLength": 10,
        "dashes": false,
        "datasource": "Prometheus",
        "fieldConfig": {
          "defaults": {},
          "overrides": []
        },
        "fill": 1,
        "fillGradient": 0,
        "gridPos": {
          "h": 8,
          "w": 12,
          "x": 0,
          "y": 10
        },
        "hiddenSeries": false,
        "id": 14,
        "legend": {
          "avg": false,
          "current": false,
          "max": false,
          "min": false,
          "show": true,
          "total": false,
          "values": false
        },
        "lines": true,
        "linewidth": 1,
        "nullPointMode": "null",
        "options": {
          "alertThreshold": true
        },
        "percentage": false,
        "pluginVersion": "7.5.7",
        "pointradius": 2,
        "points": false,
        "renderer": "flot",
        "seriesOverrides": [],
        "spaceLength": 10,
        "stack": false,
        "steppedLine": false,
        "targets": [
          {
            "exemplar": true,
            "expr": "sum by (instance)(100 - ((node_filesystem_avail_bytes{device!~'rootfs'} * 100) / node_filesystem_size_bytes{device!~'rootfs'}))",
            "interval": "",
            "legendFormat": "{{instance}}",
            "refId": "A"
          }
        ],
        "thresholds": [
          {
            "colorMode": "critical",
            "fill": true,
            "line": true,
            "op": "gt",
            "value": 80,
            "visible": true
          }
        ],
        "timeFrom": null,
        "timeRegions": [],
        "timeShift": null,
        "title": "Disk Graph",
        "tooltip": {
          "shared": true,
          "sort": 0,
          "value_type": "individual"
        },
        "type": "graph",
        "xaxis": {
          "buckets": null,
          "mode": "time",
          "name": null,
          "show": true,
          "values": []
        },
        "yaxes": [
          {
            "$$hashKey": "object:2208",
            "format": "short",
            "label": null,
            "logBase": 1,
            "max": "100",
            "min": "0",
            "show": true
          },
          {
            "$$hashKey": "object:2209",
            "format": "short",
            "label": null,
            "logBase": 1,
            "max": null,
            "min": null,
            "show": true
          }
        ],
        "yaxis": {
          "align": false,
          "alignLevel": null
        }
      }
    ],
    "refresh": "10s",
    "schemaVersion": 27,
    "style": "dark",
    "tags": [],
    "templating": {
      "list": []
    },
    "time": {
      "from": "now-1h",
      "to": "now"
    },
    "timepicker": {},
    "timezone": "",
    "title": "Node_exporter overall",
    "uid": "REirhHR7z",
    "version": 15
  }